tg_api/__init__.py
tg_api/client.py
tg_api/exceptions.py
tg_api/tg_methods.py
tg_api/tg_types.py
tg_api-1.5.0.dist-info/METADATA
tg_api-1.5.0.dist-info/WHEEL
tg_api-1.5.0.dist-info/RECORD
