Metadata-Version: 2.1
Name: tg-api
Version: 1.5.0
Summary: Thin wrapper around Telegram Bot API
Home-page: https://pypi.org/project/tg-api/
License: GNU GPLv3
Keywords: telegram,bot,api,wrapper,asyncio
Author: Evgeny Evseev
Author-email: pelid80@gmail.com
Requires-Python: >=3.10,<4.0
Classifier: License :: Other/Proprietary License
Classifier: Programming Language :: Python :: 3
Classifier: Programming Language :: Python :: 3.10
Classifier: Programming Language :: Python :: 3.11
Classifier: Programming Language :: Python :: 3.12
Requires-Dist: httpx (>=0.24.1,<1)
Requires-Dist: pydantic (>=1.9.0,<2)
Project-URL: Documentation, https://tg-api.readthedocs.io/en/latest/index.html
Project-URL: Repository, https://gitlab.dvmn.org/dvmn-open-source-dev-tools/tg_api
